CHANGELOG.md
gibihm/__init__.py
gibihm/cli.py
gibihm/gitlab.py
gibihm/task.py
gibihm/util.py
gibihm-0.1.1.post2.dist-info/entry_points.txt
gibihm-0.1.1.post2.dist-info/LICENSE
gibihm-0.1.1.post2.dist-info/WHEEL
gibihm-0.1.1.post2.dist-info/METADATA
gibihm-0.1.1.post2.dist-info/RECORD
