Metadata-Version: 2.1
Name: gibihm
Version: 0.1.1.post2
Summary: GitLab Issue Bot for Isochronal Heads-up Monitoring
Home-page: https://edugit.org/nik/gibihm
License: Apache-2.0
Author: Dominik George
Author-email: nik@naturalnet.de
Requires-Python: >=3.9,<4.0
Classifier: Development Status :: 4 - Beta
Classifier: Environment :: Console
Classifier: Intended Audience :: Developers
Classifier: Intended Audience :: System Administrators
Classifier: License :: OSI Approved :: Apache Software License
Classifier: Programming Language :: Python :: 3
Classifier: Programming Language :: Python :: 3.9
Classifier: Topic :: Utilities
Requires-Dist: PyYAML (>=5.4.1,<6.0.0)
Requires-Dist: click (>=7.1.2,<8.0.0)
Requires-Dist: click-logging (>=1.0.1,<2.0.0)
Requires-Dist: croniter (>=1.0.12,<2.0.0)
Requires-Dist: dateparser (>=1.0.0,<2.0.0)
Requires-Dist: python-gitlab (>=2.7.1,<3.0.0)
Requires-Dist: pytz (>=2021.1,<2022.0)
Project-URL: Repository, https://edugit.org/nik/gibihm
